{
  "_fv": 73,
  "_type": "potioneffect",
  "definition": {
    "effectName": "Radiation Cure",
    "icon": "radiation_cure",
    "color": {
      "value": -3342592,
      "falpha": 0.0
    },
    "isInstant": false,
    "mobEffectCategory": "BENEFICIAL",
    "renderStatusInInventory": true,
    "renderStatusInHUD": true,
    "isCuredByMilk": true,
    "isProtectedByTotem": true,
    "isCuredbyHoney": false,
    "modifiers": [],
    "onActiveTick": {
      "name": "RadiationCureOnEffectActiveTick"
    }
  }
}